{
  "project_info": {
    "project_number": "335701319595",
    "project_id": "simplemessenger-a09d5",
    "storage_bucket": "simplemessenger-a09d5.appspot.com"
  },
  "client": [
    {
      "client_info": {
        "mobilesdk_app_id": "1:335701319595:android:9056ad81524bf92fe9bcee",
        "android_client_info": {
          "package_name": "com.example.final_gram"
        }
      },
      "oauth_client": [
        {
          "client_id": "335701319595-jvqgjub7a8eub9bs0ogl0h5h3gd246lj.apps.googleusercontent.com",
          "client_type": 3
        }
      ],
      "api_key": [
        {
          "current_key": "AIzaSyAzzdI4x-tHzZRBkUto1WSTbBLBh5CzIk8"
        }
      ],
      "services": {
        "appinvite_service": {
          "other_platform_oauth_client": [
            {
              "client_id": "335701319595-jvqgjub7a8eub9bs0ogl0h5h3gd246lj.apps.googleusercontent.com",
              "client_type": 3
            }
          ]
        }
      }
    }
  ],
  "configuration_version": "1"
}